<annotation>
	<folder>VOC2007</folder>
	<filename>000025/005440.jpg</filename>
	<source>
		<database>My Database</database>
		<annotation>VOC2007</annotation>
		<image>flickr</image>
		<flickrid>NULL</flickrid>
	</source>
	<owner>
		<flickrid>NULL</flickrid>
		<name>xiaoxianyu</name>
	</owner>
	<size>
		<width>640</width>
		<height>480</height>
		<depth>3</depth>
	</size>
	<segmented>0</segmented>
	<object>
		<name>person</name>
		<pose>Unspecified</pose>
		<truncated>0</truncated>
		<difficult>0</difficult>
		<bndbox>
			<xmin>214</xmin>
			<ymin>181</ymin>
			<xmax>236</xmax>
			<ymax>216</ymax>
		</bndbox>
	</object>
	<object>
		<name>person</name>
		<pose>Unspecified</pose>
		<truncated>0</truncated>
		<difficult>0</difficult>
		<bndbox>
			<xmin>148</xmin>
			<ymin>164</ymin>
			<xmax>169</xmax>
			<ymax>221</ymax>
		</bndbox>
	</object>
	<object>
		<name>person</name>
		<pose>Unspecified</pose>
		<truncated>0</truncated>
		<difficult>0</difficult>
		<bndbox>
			<xmin>168</xmin>
			<ymin>166</ymin>
			<xmax>208</xmax>
			<ymax>223</ymax>
		</bndbox>
	</object>
	<object>
		<name>person</name>
		<pose>Unspecified</pose>
		<truncated>0</truncated>
		<difficult>0</difficult>
		<bndbox>
			<xmin>475</xmin>
			<ymin>167</ymin>
			<xmax>493</xmax>
			<ymax>214</ymax>
		</bndbox>
	</object>
	<object>
		<name>person</name>
		<pose>Unspecified</pose>
		<truncated>0</truncated>
		<difficult>0</difficult>
		<bndbox>
			<xmin>434</xmin>
			<ymin>174</ymin>
			<xmax>445</xmax>
			<ymax>205</ymax>
		</bndbox>
	</object>
	<object>
		<name>person</name>
		<pose>Unspecified</pose>
		<truncated>0</truncated>
		<difficult>0</difficult>
		<bndbox>
			<xmin>478</xmin>
			<ymin>166</ymin>
			<xmax>517</xmax>
			<ymax>216</ymax>
		</bndbox>
	</object>
</annotation>
