<annotation>
	<folder>000021</folder>
	<filename>000571</filename>
	<path>/home/superhui/caffe/Faster_rcnn/trafficsing_model/py-faster-rcnn/lib/datasets/VOCdevkit/VOC2007/JPEGImages/000021/000571.jpg</path>
	<source>
		<database>Unknown</database>
	</source>
	<size>
		<width>1536</width>
		<height>1024</height>
		<depth>3</depth>
	</size>
	<segmented>0</segmented>
	<object>
		<name>trafficsign</name>
		<pose>Unspecified</pose>
		<truncated>0</truncated>
		<difficult>0</difficult>
		<bndbox>
			<xmin>728</xmin>
			<ymin>485</ymin>
			<xmax>765</xmax>
			<ymax>517</ymax>
		</bndbox>
	</object>
	<object>
		<name>trafficsign</name>
		<pose>Unspecified</pose>
		<truncated>0</truncated>
		<difficult>0</difficult>
		<bndbox>
			<xmin>663</xmin>
			<ymin>250</ymin>
			<xmax>689</xmax>
			<ymax>314</ymax>
		</bndbox>
	</object>
	<object>
		<name>trafficsign</name>
		<pose>Unspecified</pose>
		<truncated>0</truncated>
		<difficult>0</difficult>
		<bndbox>
			<xmin>1353</xmin>
			<ymin>427</ymin>
			<xmax>1378</xmax>
			<ymax>477</ymax>
		</bndbox>
	</object>
</annotation>
