<annotation>
	<folder>000021</folder>
	<filename>004034</filename>
	<path>Z:\mswap\000021\004034.jpg</path>
	<source>
		<database>Unknown</database>
	</source>
	<size>
		<width>1536</width>
		<height>1024</height>
		<depth>3</depth>
	</size>
	<segmented>0</segmented>
	<object>
		<name>trafficsign</name>
		<pose>Unspecified</pose>
		<truncated>0</truncated>
		<difficult>0</difficult>
		<bndbox>
			<xmin>825</xmin>
			<ymin>487</ymin>
			<xmax>862</xmax>
			<ymax>523</ymax>
		</bndbox>
	</object>
	<object>
		<name>trafficsign</name>
		<pose>Unspecified</pose>
		<truncated>0</truncated>
		<difficult>0</difficult>
		<bndbox>
			<xmin>973</xmin>
			<ymin>272</ymin>
			<xmax>1003</xmax>
			<ymax>334</ymax>
		</bndbox>
	</object>
	<object>
		<name>trafficsign</name>
		<pose>Unspecified</pose>
		<truncated>0</truncated>
		<difficult>0</difficult>
		<bndbox>
			<xmin>1125</xmin>
			<ymin>276</ymin>
			<xmax>1156</xmax>
			<ymax>340</ymax>
		</bndbox>
	</object>
</annotation>
