<annotation>
	<folder>000021</folder>
	<filename>011164</filename>
	<path>Z:\mswap\000021\011164.jpg</path>
	<source>
		<database>Unknown</database>
	</source>
	<size>
		<width>1536</width>
		<height>1024</height>
		<depth>3</depth>
	</size>
	<segmented>0</segmented>
	<object>
		<name>trafficsign</name>
		<pose>Unspecified</pose>
		<truncated>0</truncated>
		<difficult>0</difficult>
		<bndbox>
			<xmin>891</xmin>
			<ymin>400</ymin>
			<xmax>977</xmax>
			<ymax>440</ymax>
		</bndbox>
	</object>
	<object>
		<name>trafficsign</name>
		<pose>Unspecified</pose>
		<truncated>0</truncated>
		<difficult>0</difficult>
		<bndbox>
			<xmin>1207</xmin>
			<ymin>470</ymin>
			<xmax>1241</xmax>
			<ymax>503</ymax>
		</bndbox>
	</object>
</annotation>
