<annotation>
	<folder>VOC2007</folder>
	<filename>trafficsign_20160205/000008/000028.jpg</filename>
	<source>
		<database>My Database</database>
		<annotation>VOC2007</annotation>
		<image>flickr</image>
		<flickrid>NULL</flickrid>
	</source>
	<owner>
		<flickrid>NULL</flickrid>
		<name>xiaoxianyu</name>
	</owner>
	<size>
		<width>1280</width>
		<height>720</height>
		<depth>3</depth>
	</size>
	<segmented>0</segmented>
	<object>
		<name>trafficsign</name>
		<pose>Unspecified</pose>
		<truncated>0</truncated>
		<difficult>0</difficult>
		<bndbox>
			<xmin>921</xmin>
			<ymin>323</ymin>
			<xmax>942</xmax>
			<ymax>343</ymax>
		</bndbox>
	</object>
	<object>
		<name>trafficsign</name>
		<pose>Unspecified</pose>
		<truncated>0</truncated>
		<difficult>0</difficult>
		<bndbox>
			<xmin>1035</xmin>
			<ymin>389</ymin>
			<xmax>1055</xmax>
			<ymax>412</ymax>
		</bndbox>
	</object>
	<object>
		<name>trafficsign</name>
		<pose>Unspecified</pose>
		<truncated>0</truncated>
		<difficult>0</difficult>
		<bndbox>
			<xmin>1102</xmin>
			<ymin>286</ymin>
			<xmax>1137</xmax>
			<ymax>392</ymax>
		</bndbox>
	</object>
	<object>
		<name>trafficsign</name>
		<pose>Unspecified</pose>
		<truncated>0</truncated>
		<difficult>0</difficult>
		<bndbox>
			<xmin>1255</xmin>
			<ymin>242</ymin>
			<xmax>1277</xmax>
			<ymax>285</ymax>
		</bndbox>
	</object>
	<object>
		<name>trafficsign</name>
		<pose>Unspecified</pose>
		<truncated>0</truncated>
		<difficult>0</difficult>
		<bndbox>
			<xmin>874</xmin>
			<ymin>323</ymin>
			<xmax>887</xmax>
			<ymax>347</ymax>
		</bndbox>
	</object>
	<object>
		<name>trafficsign</name>
		<pose>Unspecified</pose>
		<truncated>0</truncated>
		<difficult>0</difficult>
		<bndbox>
			<xmin>845</xmin>
			<ymin>389</ymin>
			<xmax>860</xmax>
			<ymax>430</ymax>
		</bndbox>
	</object>
	<object>
		<name>trafficsign</name>
		<pose>Unspecified</pose>
		<truncated>0</truncated>
		<difficult>0</difficult>
		<bndbox>
			<xmin>670</xmin>
			<ymin>432</ymin>
			<xmax>680</xmax>
			<ymax>457</ymax>
		</bndbox>
	</object>
	<object>
		<name>trafficsign</name>
		<pose>Unspecified</pose>
		<truncated>0</truncated>
		<difficult>0</difficult>
		<bndbox>
			<xmin>844</xmin>
			<ymin>391</ymin>
			<xmax>856</xmax>
			<ymax>410</ymax>
		</bndbox>
	</object>
	<object>
		<name>trafficsign</name>
		<pose>Unspecified</pose>
		<truncated>0</truncated>
		<difficult>0</difficult>
		<bndbox>
			<xmin>848</xmin>
			<ymin>415</ymin>
			<xmax>858</xmax>
			<ymax>427</ymax>
		</bndbox>
	</object>
	<object>
		<name>trafficsign</name>
		<pose>Unspecified</pose>
		<truncated>0</truncated>
		<difficult>0</difficult>
		<bndbox>
			<xmin>383</xmin>
			<ymin>375</ymin>
			<xmax>388</xmax>
			<ymax>388</ymax>
		</bndbox>
	</object>
	<object>
		<name>trafficsign</name>
		<pose>Unspecified</pose>
		<truncated>0</truncated>
		<difficult>0</difficult>
		<bndbox>
			<xmin>425</xmin>
			<ymin>380</ymin>
			<xmax>433</xmax>
			<ymax>394</ymax>
		</bndbox>
	</object>
	<object>
		<name>trafficsign</name>
		<pose>Unspecified</pose>
		<truncated>0</truncated>
		<difficult>0</difficult>
		<bndbox>
			<xmin>227</xmin>
			<ymin>400</ymin>
			<xmax>236</xmax>
			<ymax>417</ymax>
		</bndbox>
	</object>
</annotation>