<annotation>
	<folder>VOC2007</folder>
	<filename>000026/002411.jpg</filename>
	<source>
		<database>My Database</database>
		<annotation>VOC2007</annotation>
		<image>flickr</image>
		<flickrid>NULL</flickrid>
	</source>
	<owner>
		<flickrid>NULL</flickrid>
		<name>xiaoxianyu</name>
	</owner>
	<size>
		<width>1536</width>
		<height>1024</height>
		<depth>3</depth>
	</size>
	<segmented>0</segmented>
	<object>
		<name>car</name>
		<pose>Unspecified</pose>
		<truncated>0</truncated>
		<difficult>0</difficult>
		<bndbox>
			<xmin>1116</xmin>
			<ymin>531</ymin>
			<xmax>1263</xmax>
			<ymax>699</ymax>
		</bndbox>
	</object>
	<object>
		<name>car</name>
		<pose>Unspecified</pose>
		<truncated>0</truncated>
		<difficult>0</difficult>
		<bndbox>
			<xmin>315</xmin>
			<ymin>519</ymin>
			<xmax>492</xmax>
			<ymax>689</ymax>
		</bndbox>
	</object>
	<object>
		<name>car</name>
		<pose>Unspecified</pose>
		<truncated>0</truncated>
		<difficult>0</difficult>
		<bndbox>
			<xmin>751</xmin>
			<ymin>521</ymin>
			<xmax>1053</xmax>
			<ymax>740</ymax>
		</bndbox>
	</object>
	<object>
		<name>car</name>
		<pose>Unspecified</pose>
		<truncated>0</truncated>
		<difficult>0</difficult>
		<bndbox>
			<xmin>616</xmin>
			<ymin>517</ymin>
			<xmax>704</xmax>
			<ymax>572</ymax>
		</bndbox>
	</object>
</annotation>
