<annotation>
	<folder>000022</folder>
	<filename>001705</filename>
	<path>Z:\mswap\000022\001705.jpg</path>
	<source>
		<database>Unknown</database>
	</source>
	<size>
		<width>1536</width>
		<height>1024</height>
		<depth>3</depth>
	</size>
	<segmented>0</segmented>
	<object>
		<name>trafficsign</name>
		<pose>Unspecified</pose>
		<truncated>0</truncated>
		<difficult>0</difficult>
		<bndbox>
			<xmin>848</xmin>
			<ymin>301</ymin>
			<xmax>935</xmax>
			<ymax>361</ymax>
		</bndbox>
	</object>
	<object>
		<name>trafficsign</name>
		<pose>Unspecified</pose>
		<truncated>0</truncated>
		<difficult>0</difficult>
		<bndbox>
			<xmin>953</xmin>
			<ymin>320</ymin>
			<xmax>1034</xmax>
			<ymax>370</ymax>
		</bndbox>
	</object>
	<object>
		<name>trafficsign</name>
		<pose>Unspecified</pose>
		<truncated>0</truncated>
		<difficult>0</difficult>
		<bndbox>
			<xmin>1059</xmin>
			<ymin>342</ymin>
			<xmax>1128</xmax>
			<ymax>394</ymax>
		</bndbox>
	</object>
</annotation>
