<annotation>
	<folder>000022</folder>
	<filename>001992</filename>
	<path>Z:\mswap\000022\001992.jpg</path>
	<source>
		<database>Unknown</database>
	</source>
	<size>
		<width>1536</width>
		<height>1024</height>
		<depth>3</depth>
	</size>
	<segmented>0</segmented>
	<object>
		<name>trafficsign</name>
		<pose>Unspecified</pose>
		<truncated>0</truncated>
		<difficult>0</difficult>
		<bndbox>
			<xmin>1392</xmin>
			<ymin>359</ymin>
			<xmax>1446</xmax>
			<ymax>411</ymax>
		</bndbox>
	</object>
	<object>
		<name>trafficsign</name>
		<pose>Unspecified</pose>
		<truncated>0</truncated>
		<difficult>0</difficult>
		<bndbox>
			<xmin>1392</xmin>
			<ymin>409</ymin>
			<xmax>1434</xmax>
			<ymax>456</ymax>
		</bndbox>
	</object>
</annotation>
