<annotation>
	<folder>VOC2007</folder>
	<filename>trafficsign_20160205/000015/000151.jpg</filename>
	<source>
		<database>My Database</database>
		<annotation>VOC2007</annotation>
		<image>flickr</image>
		<flickrid>NULL</flickrid>
	</source>
	<owner>
		<flickrid>NULL</flickrid>
		<name>xiaoxianyu</name>
	</owner>
	<size>
		<width>1280</width>
		<height>720</height>
		<depth>3</depth>
	</size>
	<segmented>0</segmented>
	<object>
		<name>trafficsign</name>
		<pose>Unspecified</pose>
		<truncated>0</truncated>
		<difficult>0</difficult>
		<bndbox>
			<xmin>42</xmin>
			<ymin>223</ymin>
			<xmax>94</xmax>
			<ymax>350</ymax>
		</bndbox>
	</object>
	<object>
		<name>trafficsign</name>
		<pose>Unspecified</pose>
		<truncated>0</truncated>
		<difficult>0</difficult>
		<bndbox>
			<xmin>617</xmin>
			<ymin>413</ymin>
			<xmax>625</xmax>
			<ymax>430</ymax>
		</bndbox>
	</object>
	<object>
		<name>trafficsign</name>
		<pose>Unspecified</pose>
		<truncated>0</truncated>
		<difficult>0</difficult>
		<bndbox>
			<xmin>628</xmin>
			<ymin>412</ymin>
			<xmax>637</xmax>
			<ymax>430</ymax>
		</bndbox>
	</object>
	<object>
		<name>trafficsign</name>
		<pose>Unspecified</pose>
		<truncated>0</truncated>
		<difficult>0</difficult>
		<bndbox>
			<xmin>1086</xmin>
			<ymin>352</ymin>
			<xmax>1109</xmax>
			<ymax>394</ymax>
		</bndbox>
	</object>
	<object>
		<name>trafficsign</name>
		<pose>Unspecified</pose>
		<truncated>0</truncated>
		<difficult>0</difficult>
		<bndbox>
			<xmin>1098</xmin>
			<ymin>397</ymin>
			<xmax>1115</xmax>
			<ymax>426</ymax>
		</bndbox>
	</object>
	<object>
		<name>trafficsign</name>
		<pose>Unspecified</pose>
		<truncated>0</truncated>
		<difficult>0</difficult>
		<bndbox>
			<xmin>1062</xmin>
			<ymin>355</ymin>
			<xmax>1076</xmax>
			<ymax>378</ymax>
		</bndbox>
	</object>
</annotation>