<annotation>
	<folder>VOC2007</folder>
	<filename>000027/004479.jpg</filename>
	<source>
		<database>My Database</database>
		<annotation>VOC2007</annotation>
		<image>flickr</image>
		<flickrid>NULL</flickrid>
	</source>
	<owner>
		<flickrid>NULL</flickrid>
		<name>xiaoxianyu</name>
	</owner>
	<size>
		<width>1536</width>
		<height>1024</height>
		<depth>3</depth>
	</size>
	<segmented>0</segmented>
	<object>
		<name>car</name>
		<pose>Unspecified</pose>
		<truncated>0</truncated>
		<difficult>0</difficult>
		<bndbox>
			<xmin>951</xmin>
			<ymin>533</ymin>
			<xmax>1473</xmax>
			<ymax>772</ymax>
		</bndbox>
	</object>
	<object>
		<name>car</name>
		<pose>Unspecified</pose>
		<truncated>0</truncated>
		<difficult>0</difficult>
		<bndbox>
			<xmin>620</xmin>
			<ymin>517</ymin>
			<xmax>800</xmax>
			<ymax>631</ymax>
		</bndbox>
	</object>
	<object>
		<name>car</name>
		<pose>Unspecified</pose>
		<truncated>0</truncated>
		<difficult>0</difficult>
		<bndbox>
			<xmin>1335</xmin>
			<ymin>546</ymin>
			<xmax>1535</xmax>
			<ymax>689</ymax>
		</bndbox>
	</object>
	<object>
		<name>car</name>
		<pose>Unspecified</pose>
		<truncated>0</truncated>
		<difficult>0</difficult>
		<bndbox>
			<xmin>827</xmin>
			<ymin>485</ymin>
			<xmax>993</xmax>
			<ymax>587</ymax>
		</bndbox>
	</object>
</annotation>
